applaud/__init__.py
applaud/connection.py
applaud/endpoints/__init__.py
applaud/endpoints/age_rating_declarations.py
applaud/endpoints/app_categories.py
applaud/endpoints/app_clip_advanced_experience_images.py
applaud/endpoints/app_clip_advanced_experiences.py
applaud/endpoints/app_clip_app_store_review_details.py
applaud/endpoints/app_clip_default_experience_localizations.py
applaud/endpoints/app_clip_default_experiences.py
applaud/endpoints/app_clip_header_images.py
applaud/endpoints/app_clips.py
applaud/endpoints/app_encryption_declarations.py
applaud/endpoints/app_info_localizations.py
applaud/endpoints/app_infos.py
applaud/endpoints/app_pre_orders.py
applaud/endpoints/app_preview_sets.py
applaud/endpoints/app_previews.py
applaud/endpoints/app_price_points.py
applaud/endpoints/app_price_tiers.py
applaud/endpoints/app_prices.py
applaud/endpoints/app_screenshot_sets.py
applaud/endpoints/app_screenshots.py
applaud/endpoints/app_store_review_attachments.py
applaud/endpoints/app_store_review_details.py
applaud/endpoints/app_store_version_localizations.py
applaud/endpoints/app_store_version_phased_releases.py
applaud/endpoints/app_store_version_release_requests.py
applaud/endpoints/app_store_version_submissions.py
applaud/endpoints/app_store_versions.py
applaud/endpoints/apps.py
applaud/endpoints/base.py
applaud/endpoints/beta_app_clip_invocation_localizations.py
applaud/endpoints/beta_app_clip_invocations.py
applaud/endpoints/beta_app_localizations.py
applaud/endpoints/beta_app_review_details.py
applaud/endpoints/beta_app_review_submissions.py
applaud/endpoints/beta_build_localizations.py
applaud/endpoints/beta_groups.py
applaud/endpoints/beta_license_agreements.py
applaud/endpoints/beta_tester_invitations.py
applaud/endpoints/beta_testers.py
applaud/endpoints/build_beta_details.py
applaud/endpoints/build_beta_notifications.py
applaud/endpoints/build_bundles.py
applaud/endpoints/builds.py
applaud/endpoints/bundle_id_capabilities.py
applaud/endpoints/bundle_ids.py
applaud-0.9.4.dist-info/LICENSE
applaud-0.9.4.dist-info/WHEEL
applaud-0.9.4.dist-info/METADATA
applaud-0.9.4.dist-info/RECORD
