Metadata-Version: 2.1
Name: applaud
Version: 0.9.4
Summary: The Python SDK to work with the App Store Connect API from Apple.
Home-page: https://github.com/codinn/applaud
License: MIT
Author: Yang.Y
Author-email: yang@yangyubo.com
Requires-Python: >=3.9,<4.0
Classifier: Development Status :: 3 - Alpha
Classifier: License :: OSI Approved :: MIT License
Classifier: Programming Language :: Python :: 3
Classifier: Programming Language :: Python :: 3 :: Only
Classifier: Programming Language :: Python :: 3.10
Classifier: Programming Language :: Python :: 3.9
Classifier: Topic :: Software Development :: Libraries :: Python Modules
Requires-Dist: Deprecated (>=1.2.13,<2.0.0)
Requires-Dist: authlib (>=0.15.5,<0.16.0)
Requires-Dist: pydantic[email] (>=1.9.0,<2.0.0)
Requires-Dist: requests (>=2.27.0,<3.0.0)
Project-URL: Repository, https://github.com/codinn/applaud.git
